dlt_pipedrive_source/__init__.py
dlt_pipedrive_source/_helpers.py
dlt_pipedrive_source/extract_sample_data.py
dlt_pipedrive_source/extract_schema.py
dlt_pipedrive_source/mock_source.py
dlt_pipedrive_source/pipedrive_source.py
dlt_pipedrive_source/run_pipeline.py
dlt_pipedrive_source/sample_data/deal.jsonl
dlt_pipedrive_source/sample_data/deal_flow.jsonl
dlt_pipedrive_source/sample_data/deal_participant.jsonl
dlt_pipedrive_source/schema.yml
dlt_pipedrive_source-0.0.17.dist-info/LICENSE
dlt_pipedrive_source-0.0.17.dist-info/WHEEL
dlt_pipedrive_source-0.0.17.dist-info/METADATA
dlt_pipedrive_source-0.0.17.dist-info/RECORD
